fastack/__init__.py
fastack/__main__.py
fastack/app.py
fastack/cli.py
fastack/constants.py
fastack/context.py
fastack/controller.py
fastack/decorators.py
fastack/globals.py
fastack/local.py
fastack/middleware/__init__.py
fastack/middleware/base.py
fastack/mixins.py
fastack/models.py
fastack/pagination.py
fastack/py.typed
fastack/utils.py
fastack-4.5.0.dist-info/entry_points.txt
fastack-4.5.0.dist-info/LICENSE
fastack-4.5.0.dist-info/WHEEL
fastack-4.5.0.dist-info/METADATA
fastack-4.5.0.dist-info/RECORD
