Metadata-Version: 2.1
Name: fastack
Version: 4.5.0
Summary: fastack is an intuitive framework based on FastAPI
Home-page: https://github.com/fastack-dev/fastack
License: MIT
Author: aprilahijriyan
Author-email: 37798612+aprilahijriyan@users.noreply.github.com
Maintainer: aprilahijriyan
Maintainer-email: 37798612+aprilahijriyan@users.noreply.github.com
Requires-Python: >=3.7,<4.0.0
Classifier: Development Status :: 4 - Beta
Classifier: Environment :: Web Environment
Classifier: Intended Audience :: Developers
Classifier: Intended Audience :: Information Technology
Classifier: Intended Audience :: System Administrators
Classifier: License :: OSI Approved :: MIT License
Classifier: Operating System :: OS Independent
Classifier: Programming Language :: Python
Classifier: Programming Language :: Python :: 3
Classifier: Programming Language :: Python :: 3 :: Only
Classifier: Programming Language :: Python :: 3.10
Classifier: Programming Language :: Python :: 3.7
Classifier: Programming Language :: Python :: 3.8
Classifier: Programming Language :: Python :: 3.9
Classifier: Topic :: Internet
Classifier: Topic :: Software Development
Classifier: Topic :: Software Development :: Libraries
Classifier: Topic :: Software Development :: Libraries :: Application Frameworks
Classifier: Topic :: Software Development :: Libraries :: Python Modules
Requires-Dist: asgi-lifespan (>=1.0.1,<2.0.0)
Requires-Dist: cookiecutter (>=1.7.3,<2.0.0)
Requires-Dist: fastapi (>=0.72.0,<0.73.0)
Requires-Dist: typer (>=0.4.0,<0.5.0)
Requires-Dist: uvicorn[standard] (>=0.16.0,<0.17.0)
Project-URL: Bug Tracker, https://github.com/fastack-dev/fastack/issues
Project-URL: Repository, https://github.com/fastack-dev/fastack
